README.md
setup.py
graphviz_sql/__init__.py
graphviz_sql/extract.py
graphviz_sql.egg-info/PKG-INFO
graphviz_sql.egg-info/SOURCES.txt
graphviz_sql.egg-info/dependency_links.txt
graphviz_sql.egg-info/top_level.txt