Metadata-Version: 2.1
Name: graphviz-sql
Version: 0.1.8
Summary: 将tree.export_graphviz构建决策树代码转换为标准sql
Home-page: https://github.com/WangxuP/graphviz_sql
Author: wangxup
Author-email: wang_xup@163.com
License: UNKNOWN
Keywords: None
Platform: any
